{
   "palette": [
      {
         "char": "X",
         "variant": "windpunk:end_bricks",
         "damaged": "minecraft:iron_bars"
      },
      {
         "char": "$",
         "block": "minecraft:purpur_pillar",
         "damaged": "minecraft:iron_bars"
      },
      {
         "char": "#",
         "variant": "windpunk:end_bricks",
         "damaged": "minecraft:iron_bars"
      },
      {
         "char": "}",
         "variant": "windpunk:end_bricks_rubble",
         "damaged": "minecraft:iron_bars"
      }
   ]
}